btdtrigger/__init__.py
btdtrigger/cli.py
btdtrigger/config_parser.py
btdtrigger/listener.py
btdtrigger/models.py
btdtrigger-0.1.3.dist-info/licenses/LICENSE
btdtrigger-0.1.3.dist-info/METADATA
btdtrigger-0.1.3.dist-info/WHEEL
btdtrigger-0.1.3.dist-info/entry_points.txt
btdtrigger-0.1.3.dist-info/top_level.txt
btdtrigger-0.1.3.dist-info/RECORD
