Metadata-Version: 2.4
Name: btdtrigger
Version: 0.1.3
Summary: Simple utility to trigger commands when bluetooth devices are seen on Linux
Requires-Python: >=3.11
License-File: LICENSE
Requires-Dist: typer
Dynamic: license-file
